KubiScanPyPi/KubiScan.py
KubiScanPyPi/__init__.py
KubiScanPyPi/static_risky_roles.py
KubiScanPyPi/api/__init__.py
KubiScanPyPi/api/api_client.py
KubiScanPyPi/api/api_client_temp.py
KubiScanPyPi/engine/__init__.py
KubiScanPyPi/engine/container.py
KubiScanPyPi/engine/jwt_token.py
KubiScanPyPi/engine/pod.py
KubiScanPyPi/engine/priority.py
KubiScanPyPi/engine/privleged_containers.py
KubiScanPyPi/engine/role.py
KubiScanPyPi/engine/role_binding.py
KubiScanPyPi/engine/rule.py
KubiScanPyPi/engine/subject.py
KubiScanPyPi/engine/utils.py
KubiScanPyPi/misc/__init__.py
KubiScanPyPi/misc/colours.py
KubiScanPyPi/misc/constants.py
KubiScanPyPiTest-0.1.48.dist-info/METADATA
KubiScanPyPiTest-0.1.48.dist-info/WHEEL
KubiScanPyPiTest-0.1.48.dist-info/top_level.txt
KubiScanPyPiTest-0.1.48.dist-info/RECORD
